README.md
setup.py
Scripts/__init__.py
Scripts/__main__.py
Scripts/aparatApi.py
Scripts/aparatLinksFinder.py
Scripts/aparat_dl.py
aparati.egg-info/PKG-INFO
aparati.egg-info/SOURCES.txt
aparati.egg-info/dependency_links.txt
aparati.egg-info/entry_points.txt
aparati.egg-info/requires.txt
aparati.egg-info/top_level.txt