Metadata-Version: 2.1
Name: aparati
Version: 2.1.1
Summary:  this tools is for download video from aparat.com (an iranian website)
Home-page: https://github.com/mehdigdr/aparat-dl
Download-URL: https://github.com/mehdigdr/aparat-dl/archive/v2.1.1tar.gz
Author: mehdi
Author-email: thisisnotreall@dont.com
License: MIT
Keywords: AparatDL,aparat,aparat_dowoloader
Classifier: Programming Language :: Python :: 3.6
Classifier: Development Status :: 5 - Production/Stable
Classifier: Operating System :: OS Independent
Classifier: License :: OSI Approved :: MIT License
